[
   {
      "class":"org.sdmlib.openbank.Account",
      "id":"demo.A1",
      "prop":{
         "balance":540,
         "creationdate":{
            "class":"java.util.Date",
            "id":"demo.D2"
         },
         "owner":{
            "class":"org.sdmlib.openbank.User",
            "id":"demo.U3"
         },
         "credit":[
            {
               "class":"org.sdmlib.openbank.Transaction",
               "id":"demo.T4"
            },
            {
               "class":"org.sdmlib.openbank.Transaction",
               "id":"demo.T5"
            }
         ],
         "debit":[
            {
               "class":"org.sdmlib.openbank.Transaction",
               "id":"demo.T6"
            }
         ]
      }
   },
   {"class":"java.util.Date"},
   {
      "class":"org.sdmlib.openbank.User",
      "id":"demo.U3",
      "prop":{
         "name":"Tom",
         "UserID":"tb12",
         "account":[
            {
               "class":"org.sdmlib.openbank.Account",
               "id":"demo.A7"
            },
            {
               "class":"org.sdmlib.openbank.Account",
               "id":"demo.A1"
            }
         ]
      }
   },
   {
      "class":"org.sdmlib.openbank.Transaction",
      "id":"demo.T4",
      "prop":{
         "amount":50,
         "date":{
            "class":"java.util.Date",
            "id":"demo.D2"
         },
         "time":{
            "class":"java.util.Date",
            "id":"demo.D8"
         },
         "note":"Deposit Trans 1",
         "fromAccount":{
            "class":"org.sdmlib.openbank.Account",
            "id":"demo.A1"
         }
      }
   },
   {
      "class":"org.sdmlib.openbank.Transaction",
      "id":"demo.T5",
      "prop":{
         "amount":20,
         "date":{
            "class":"java.util.Date",
            "id":"demo.D2"
         },
         "time":{
            "class":"java.util.Date",
            "id":"demo.D9"
         },
         "note":"Deposit Trans 2",
         "fromAccount":{
            "class":"org.sdmlib.openbank.Account",
            "id":"demo.A1"
         }
      }
   },
   {
      "class":"org.sdmlib.openbank.Transaction",
      "id":"demo.T6",
      "prop":{
         "amount":40,
         "date":{
            "class":"java.util.Date",
            "id":"demo.D2"
         },
         "time":{
            "class":"java.util.Date",
            "id":"demo.D10"
         },
         "note":"Withdraw Trans 3",
         "toAccount":{
            "class":"org.sdmlib.openbank.Account",
            "id":"demo.A1"
         }
      }
   },
   {
      "class":"org.sdmlib.openbank.Account",
      "id":"demo.A7",
      "prop":{
         "accountnum":1,
         "owner":{
            "class":"org.sdmlib.openbank.User",
            "id":"demo.U3"
         }
      }
   },
   {"class":"java.util.Date"},
   {"class":"java.util.Date"},
   {"class":"java.util.Date"},
   {"class":"java.util.Date"},
   {"class":"java.util.Date"},
   {"class":"java.util.Date"}
]